swarmauri_vectorstore_doc2vec/Doc2VecVectorStore.py
swarmauri_vectorstore_doc2vec/__init__.py
swarmauri_vectorstore_doc2vec-0.7.5.dist-info/LICENSE
swarmauri_vectorstore_doc2vec-0.7.5.dist-info/METADATA
swarmauri_vectorstore_doc2vec-0.7.5.dist-info/WHEEL
swarmauri_vectorstore_doc2vec-0.7.5.dist-info/entry_points.txt
swarmauri_vectorstore_doc2vec-0.7.5.dist-info/RECORD
